{
  "entries": [
    {
      "encounter": "kanto_common_fish",
      "pokemon": "magikarp",
      "min_level": 5,
      "max_level": 15,
      "slots": 40,
      "held_item_groups": "",
      "morning_allowed": true,
      "day_allowed": true,
      "night_allowed": true
    },
    {
      "encounter": "kanto_common_fish",
      "pokemon": "poliwag",
      "min_level": 5,
      "max_level": 15,
      "slots": 25,
      "held_item_groups": "",
      "morning_allowed": true,
      "day_allowed": true,
      "night_allowed": true
    },
    {
      "encounter": "kanto_common_fish",
      "pokemon": "krabby",
      "min_level": 10,
      "max_level": 20,
      "slots": 20,
      "held_item_groups": "",
      "morning_allowed": true,
      "day_allowed": true,
      "night_allowed": true
    },
    {
      "encounter": "kanto_common_fish",
      "pokemon": "goldeen",
      "min_level": 10,
      "max_level": 20,
      "slots": 25,
      "held_item_groups": "",
      "morning_allowed": true,
      "day_allowed": true,
      "night_allowed": false
    },
    {
      "encounter": "kanto_common_fish",
      "pokemon": "tentacool",
      "min_level": 10,
      "max_level": 20,
      "slots": 20,
      "held_item_groups": "",
      "morning_allowed": false,
      "day_allowed": true,
      "night_allowed": false
    },
    {
      "encounter": "kanto_common_fish",
      "pokemon": "psyduck",
      "min_level": 15,
      "max_level": 25,
      "slots": 15,
      "held_item_groups": "",
      "morning_allowed": true,
      "day_allowed": true,
      "night_allowed": false
    },
    {
      "encounter": "kanto_common_fish",
      "pokemon": "slowpoke",
      "min_level": 15,
      "max_level": 25,
      "slots": 20,
      "held_item_groups": "",
      "morning_allowed": false,
      "day_allowed": false,
      "night_allowed": true
    },
    {
      "encounter": "kanto_common_fish",
      "pokemon": "dratini",
      "min_level": 15,
      "max_level": 20,
      "slots": 1,
      "held_item_groups": "",
      "morning_allowed": false,
      "day_allowed": false,
      "night_allowed": true
    },
    {
      "encounter": "shared_lilypad",
      "pokemon": "wooper",
      "min_level": 5,
      "max_level": 15,
      "slots": 30,
      "held_item_groups": "",
      "morning_allowed": true,
      "day_allowed": true,
      "night_allowed": true
    },
    {
      "encounter": "shared_lilypad",
      "pokemon": "marill",
      "min_level": 10,
      "max_level": 20,
      "slots": 10,
      "held_item_groups": "",
      "morning_allowed": true,
      "day_allowed": true,
      "night_allowed": true
    },
    {
      "encounter": "shared_lilypad",
      "pokemon": "poliwag",
      "min_level": 5,
      "max_level": 15,
      "slots": 40,
      "held_item_groups": "",
      "morning_allowed": true,
      "day_allowed": true,
      "night_allowed": true
    },
    {
      "encounter": "shared_lilypad",
      "pokemon": "psyduck",
      "min_level": 14,
      "max_level": 24,
      "slots": 20,
      "held_item_groups": "",
      "morning_allowed": true,
      "day_allowed": true,
      "night_allowed": true
    },
    {
      "encounter": "shared_rocksmash",
      "pokemon": "geodude",
      "min_level": 5,
      "max_level": 15,
      "slots": 40,
      "held_item_groups": "",
      "morning_allowed": true,
      "day_allowed": true,
      "night_allowed": true
    },
    {
      "encounter": "shared_rocksmash",
      "pokemon": "onix",
      "min_level": 10,
      "max_level": 20,
      "slots": 28,
      "held_item_groups": "",
      "morning_allowed": true,
      "day_allowed": true,
      "night_allowed": true
    },
    {
      "encounter": "shared_rocksmash",
      "pokemon": "graveler",
      "min_level": 20,
      "max_level": 30,
      "slots": 15,
      "held_item_groups": "",
      "morning_allowed": true,
      "day_allowed": true,
      "night_allowed": true
    },
    {
      "encounter": "kanto_route1_land",
      "pokemon": "pidgey",
      "min_level": 3,
      "max_level": 4,
      "slots": 45,
      "held_item_groups": "",
      "morning_allowed": true,
      "day_allowed": true,
      "night_allowed": false
    },
    {
      "encounter": "kanto_route1_land",
      "pokemon": "rattata",
      "min_level": 2,
      "max_level": 4,
      "slots": 105,
      "held_item_groups": "",
      "morning_allowed": true,
      "day_allowed": true,
      "night_allowed": true
    },
    {
      "encounter": "kanto_route1_land",
      "pokemon": "caterpie",
      "min_level": 3,
      "max_level": 5,
      "slots": 70,
      "held_item_groups": "",
      "morning_allowed": true,
      "day_allowed": true,
      "night_allowed": true
    },
    {
      "encounter": "kanto_route1_land",
      "pokemon": "weedle",
      "min_level": 3,
      "max_level": 4,
      "slots": 65,
      "held_item_groups": "",
      "morning_allowed": true,
      "day_allowed": true,
      "night_allowed": true
    },
    {
      "encounter": "kanto_route1_land",
      "pokemon": "sentret",
      "min_level": 3,
      "max_level": 5,
      "slots": 25,
      "held_item_groups": "",
      "morning_allowed": true,
      "day_allowed": true,
      "night_allowed": true
    },
    {
      "encounter": "kanto_route1_land",
      "pokemon": "hoothoot",
      "min_level": 4,
      "max_level": 5,
      "slots": 15,
      "held_item_groups": "",
      "morning_allowed": false,
      "day_allowed": false,
      "night_allowed": true
    },
    {
      "encounter": "kanto_route1_land",
      "pokemon": "pichu",
      "min_level": 2,
      "max_level": 4,
      "slots": 5,
      "held_item_groups": "",
      "morning_allowed": true,
      "day_allowed": false,
      "night_allowed": false
    },
    {
      "encounter": "kanto_route22_land",
      "pokemon": "spearow",
      "min_level": 4,
      "max_level": 7,
      "slots": 95,
      "held_item_groups": "",
      "morning_allowed": true,
      "day_allowed": true,
      "night_allowed": false
    },
    {
      "encounter": "kanto_route22_land",
      "pokemon": "mankey",
      "min_level": 5,
      "max_level": 7,
      "slots": 80,
      "held_item_groups": "",
      "morning_allowed": true,
      "day_allowed": true,
      "night_allowed": true
    },
    {
      "encounter": "kanto_route22_land",
      "pokemon": "rattata",
      "min_level": 4,
      "max_level": 6,
      "slots": 90,
      "held_item_groups": "",
      "morning_allowed": true,
      "day_allowed": true,
      "night_allowed": true
    },
    {
      "encounter": "kanto_route22_land",
      "pokemon": "teddiursa",
      "min_level": 5,
      "max_level": 6,
      "slots": 4,
      "held_item_groups": "",
      "morning_allowed": true,
      "day_allowed": false,
      "night_allowed": false
    },
    {
      "encounter": "kanto_route22_land",
      "pokemon": "aipom",
      "min_level": 5,
      "max_level": 6,
      "slots": 3,
      "held_item_groups": "",
      "morning_allowed": true,
      "day_allowed": true,
      "night_allowed": false
    },
    {
      "encounter": "kanto_route22_land",
      "pokemon": "ekans",
      "min_level": 5,
      "max_level": 7,
      "slots": 50,
      "held_item_groups": "",
      "morning_allowed": false,
      "day_allowed": false,
      "night_allowed": true
    },
    {
      "encounter": "kanto_route22_land",
      "pokemon": "murkrow",
      "min_level": 6,
      "max_level": 7,
      "slots": 2,
      "held_item_groups": "",
      "morning_allowed": false,
      "day_allowed": false,
      "night_allowed": true
    },
    {
      "encounter": "kanto_route22_land",
      "pokemon": "pidgey",
      "min_level": 4,
      "max_level": 6,
      "slots": 40,
      "held_item_groups": "",
      "morning_allowed": true,
      "day_allowed": true,
      "night_allowed": false
    },
    {
      "encounter": "kanto_route2_land",
      "pokemon": "caterpie",
      "min_level": 4,
      "max_level": 6,
      "slots": 80,
      "held_item_groups": "",
      "morning_allowed": true,
      "day_allowed": true,
      "night_allowed": true
    },
    {
      "encounter": "kanto_route2_land",
      "pokemon": "weedle",
      "min_level": 4,
      "max_level": 6,
      "slots": 80,
      "held_item_groups": "",
      "morning_allowed": true,
      "day_allowed": true,
      "night_allowed": true
    },
    {
      "encounter": "kanto_route2_land",
      "pokemon": "pidgey",
      "min_level": 4,
      "max_level": 7,
      "slots": 45,
      "held_item_groups": "",
      "morning_allowed": true,
      "day_allowed": true,
      "night_allowed": false
    },
    {
      "encounter": "kanto_route2_land",
      "pokemon": "pikachu",
      "min_level": 5,
      "max_level": 6,
      "slots": 15,
      "held_item_groups": "",
      "morning_allowed": false,
      "day_allowed": true,
      "night_allowed": false
    },
    {
      "encounter": "kanto_route2_land",
      "pokemon": "ledyba",
      "min_level": 5,
      "max_level": 6,
      "slots": 23,
      "held_item_groups": "",
      "morning_allowed": true,
      "day_allowed": false,
      "night_allowed": false
    },
    {
      "encounter": "kanto_route2_land",
      "pokemon": "spinarak",
      "min_level": 4,
      "max_level": 5,
      "slots": 22,
      "held_item_groups": "",
      "morning_allowed": false,
      "day_allowed": true,
      "night_allowed": true
    },
    {
      "encounter": "kanto_route2_land",
      "pokemon": "hoothoot",
      "min_level": 4,
      "max_level": 5,
      "slots": 25,
      "held_item_groups": "",
      "morning_allowed": false,
      "day_allowed": false,
      "night_allowed": true
    },
    {
      "encounter": "kanto_route2_land",
      "pokemon": "rattata",
      "min_level": 3,
      "max_level": 5,
      "slots": 50,
      "held_item_groups": "",
      "morning_allowed": true,
      "day_allowed": true,
      "night_allowed": true
    },
    {
      "encounter": "kanto_route3_land",
      "pokemon": "spearow",
      "min_level": 6,
      "max_level": 9,
      "slots": 95,
      "held_item_groups": "",
      "morning_allowed": true,
      "day_allowed": true,
      "night_allowed": true
    },
    {
      "encounter": "kanto_route3_land",
      "pokemon": "nidoran_f",
      "min_level": 6,
      "max_level": 9,
      "slots": 85,
      "held_item_groups": "",
      "morning_allowed": true,
      "day_allowed": true,
      "night_allowed": false
    },
    {
      "encounter": "kanto_route3_land",
      "pokemon": "jigglypuff",
      "min_level": 7,
      "max_level": 8,
      "slots": 40,
      "held_item_groups": "",
      "morning_allowed": true,
      "day_allowed": false,
      "night_allowed": false
    },
    {
      "encounter": "kanto_route3_land",
      "pokemon": "cleffa",
      "min_level": 5,
      "max_level": 6,
      "slots": 3,
      "held_item_groups": "",
      "morning_allowed": true,
      "day_allowed": false,
      "night_allowed": false
    },
    {
      "encounter": "kanto_route3_land",
      "pokemon": "mankey",
      "min_level": 7,
      "max_level": 8,
      "slots": 50,
      "held_item_groups": "",
      "morning_allowed": false,
      "day_allowed": true,
      "night_allowed": false
    },
    {
      "encounter": "kanto_route3_land",
      "pokemon": "zubat",
      "min_level": 7,
      "max_level": 9,
      "slots": 65,
      "held_item_groups": "",
      "morning_allowed": false,
      "day_allowed": false,
      "night_allowed": true
    },
    {
      "encounter": "kanto_route3_land",
      "pokemon": "hoothoot",
      "min_level": 6,
      "max_level": 7,
      "slots": 5,
      "held_item_groups": "",
      "morning_allowed": false,
      "day_allowed": false,
      "night_allowed": true
    },
    {
      "encounter": "kanto_route3_land",
      "pokemon": "pidgey",
      "min_level": 6,
      "max_level": 8,
      "slots": 20,
      "held_item_groups": "",
      "morning_allowed": true,
      "day_allowed": true,
      "night_allowed": false
    },
    {
      "encounter": "kanto_route4_land",
      "pokemon": "pidgey",
      "min_level": 8,
      "max_level": 10,
      "slots": 50,
      "held_item_groups": "",
      "morning_allowed": true,
      "day_allowed": true,
      "night_allowed": false
    },
    {
      "encounter": "kanto_route4_land",
      "pokemon": "ekans",
      "min_level": 8,
      "max_level": 10,
      "slots": 70,
      "held_item_groups": "",
      "morning_allowed": true,
      "day_allowed": true,
      "night_allowed": true
    },
    {
      "encounter": "kanto_route4_land",
      "pokemon": "sandshrew",
      "min_level": 8,
      "max_level": 10,
      "slots": 65,
      "held_item_groups": "",
      "morning_allowed": true,
      "day_allowed": true,
      "night_allowed": false
    },
    {
      "encounter": "kanto_route4_land",
      "pokemon": "teddiursa",
      "min_level": 7,
      "max_level": 8,
      "slots": 4,
      "held_item_groups": "",
      "morning_allowed": true,
      "day_allowed": false,
      "night_allowed": false
    },
    {
      "encounter": "kanto_route4_land",
      "pokemon": "aipom",
      "min_level": 7,
      "max_level": 8,
      "slots": 3,
      "held_item_groups": "",
      "morning_allowed": false,
      "day_allowed": true,
      "night_allowed": false
    },
    {
      "encounter": "kanto_route4_land",
      "pokemon": "murkrow",
      "min_level": 8,
      "max_level": 9,
      "slots": 4,
      "held_item_groups": "",
      "morning_allowed": false,
      "day_allowed": false,
      "night_allowed": true
    },
    {
      "encounter": "kanto_route4_land",
      "pokemon": "zubat",
      "min_level": 9,
      "max_level": 11,
      "slots": 55,
      "held_item_groups": "",
      "morning_allowed": false,
      "day_allowed": false,
      "night_allowed": true
    },
    {
      "encounter": "kanto_route4_land",
      "pokemon": "spearow",
      "min_level": 8,
      "max_level": 9,
      "slots": 55,
      "held_item_groups": "",
      "morning_allowed": true,
      "day_allowed": true,
      "night_allowed": false
    },
    {
      "encounter": "kanto_viridianforest_land",
      "pokemon": "caterpie",
      "min_level": 4,
      "max_level": 6,
      "slots": 85,
      "held_item_groups": "",
      "morning_allowed": true,
      "day_allowed": true,
      "night_allowed": true
    },
    {
      "encounter": "kanto_viridianforest_land",
      "pokemon": "weedle",
      "min_level": 4,
      "max_level": 6,
      "slots": 85,
      "held_item_groups": "",
      "morning_allowed": true,
      "day_allowed": true,
      "night_allowed": true
    },
    {
      "encounter": "kanto_viridianforest_land",
      "pokemon": "pidgey",
      "min_level": 4,
      "max_level": 6,
      "slots": 40,
      "held_item_groups": "",
      "morning_allowed": true,
      "day_allowed": true,
      "night_allowed": false
    },
    {
      "encounter": "kanto_viridianforest_land",
      "pokemon": "pikachu",
      "min_level": 5,
      "max_level": 7,
      "slots": 22,
      "held_item_groups": "",
      "morning_allowed": false,
      "day_allowed": true,
      "night_allowed": false
    },
    {
      "encounter": "kanto_viridianforest_land",
      "pokemon": "ledyba",
      "min_level": 5,
      "max_level": 6,
      "slots": 12,
      "held_item_groups": "",
      "morning_allowed": true,
      "day_allowed": false,
      "night_allowed": false
    },
    {
      "encounter": "kanto_viridianforest_land",
      "pokemon": "spinarak",
      "min_level": 5,
      "max_level": 6,
      "slots": 7,
      "held_item_groups": "",
      "morning_allowed": false,
      "day_allowed": true,
      "night_allowed": false
    },
    {
      "encounter": "kanto_viridianforest_land",
      "pokemon": "hoothoot",
      "min_level": 5,
      "max_level": 6,
      "slots": 12,
      "held_item_groups": "",
      "morning_allowed": false,
      "day_allowed": false,
      "night_allowed": true
    },
    {
      "encounter": "kanto_viridianforest_land",
      "pokemon": "kakuna",
      "min_level": 5,
      "max_level": 7,
      "slots": 35,
      "held_item_groups": "",
      "morning_allowed": false,
      "day_allowed": true,
      "night_allowed": true
    },
    {
      "encounter": "kanto_viridianforest_land",
      "pokemon": "metapod",
      "min_level": 5,
      "max_level": 7,
      "slots": 35,
      "held_item_groups": "",
      "morning_allowed": false,
      "day_allowed": true,
      "night_allowed": true
    },
    {
      "encounter": "kanto_viridianforest_land",
      "pokemon": "yanma",
      "min_level": 5,
      "max_level": 6,
      "slots": 5,
      "held_item_groups": "",
      "morning_allowed": false,
      "day_allowed": true,
      "night_allowed": false
    },
    {
      "encounter": "kanto_viridianforest_land",
      "pokemon": "venonat",
      "min_level": 5,
      "max_level": 6,
      "slots": 12,
      "held_item_groups": "",
      "morning_allowed": false,
      "day_allowed": true,
      "night_allowed": false
    },
    {
      "encounter": "kanto_route24_land",
      "pokemon": "pidgey",
      "min_level": 8,
      "max_level": 12,
      "slots": 40,
      "held_item_groups": "",
      "morning_allowed": true,
      "day_allowed": true,
      "night_allowed": false
    },
    {
      "encounter": "kanto_route24_land",
      "pokemon": "spearow",
      "min_level": 8,
      "max_level": 12,
      "slots": 80,
      "held_item_groups": "",
      "morning_allowed": false,
      "day_allowed": true,
      "night_allowed": true
    },
    {
      "encounter": "kanto_route24_land",
      "pokemon": "rattata",
      "min_level": 8,
      "max_level": 12,
      "slots": 90,
      "held_item_groups": "",
      "morning_allowed": true,
      "day_allowed": true,
      "night_allowed": true
    },
    {
      "encounter": "kanto_route24_land",
      "pokemon": "bellsprout",
      "min_level": 8,
      "max_level": 12,
      "slots": 60,
      "held_item_groups": "",
      "morning_allowed": true,
      "day_allowed": true,
      "night_allowed": false
    },
    {
      "encounter": "kanto_route24_land",
      "pokemon": "oddish",
      "min_level": 8,
      "max_level": 12,
      "slots": 50,
      "held_item_groups": "",
      "morning_allowed": true,
      "day_allowed": true,
      "night_allowed": false
    },
    {
      "encounter": "kanto_route24_land",
      "pokemon": "caterpie",
      "min_level": 8,
      "max_level": 12,
      "slots": 35,
      "held_item_groups": "",
      "morning_allowed": false,
      "day_allowed": false,
      "night_allowed": true
    },
    {
      "encounter": "kanto_route24_land",
      "pokemon": "pichu",
      "min_level": 9,
      "max_level": 12,
      "slots": 2,
      "held_item_groups": "",
      "morning_allowed": true,
      "day_allowed": true,
      "night_allowed": true
    },
    {
      "encounter": "kanto_route6_land",
      "pokemon": "pidgey",
      "min_level": 11,
      "max_level": 14,
      "slots": 35,
      "held_item_groups": "",
      "morning_allowed": true,
      "day_allowed": true,
      "night_allowed": false
    },
    {
      "encounter": "kanto_route6_land",
      "pokemon": "rattata",
      "min_level": 11,
      "max_level": 14,
      "slots": 55,
      "held_item_groups": "",
      "morning_allowed": false,
      "day_allowed": true,
      "night_allowed": true
    },
    {
      "encounter": "kanto_route6_land",
      "pokemon": "meowth",
      "min_level": 11,
      "max_level": 14,
      "slots": 60,
      "held_item_groups": "",
      "morning_allowed": true,
      "day_allowed": true,
      "night_allowed": true
    },
    {
      "encounter": "kanto_route6_land",
      "pokemon": "bellsprout",
      "min_level": 11,
      "max_level": 14,
      "slots": 35,
      "held_item_groups": "",
      "morning_allowed": true,
      "day_allowed": false,
      "night_allowed": false
    },
    {
      "encounter": "kanto_route6_land",
      "pokemon": "oddish",
      "min_level": 11,
      "max_level": 14,
      "slots": 45,
      "held_item_groups": "",
      "morning_allowed": true,
      "day_allowed": true,
      "night_allowed": false
    },
    {
      "encounter": "kanto_route6_land",
      "pokemon": "psyduck",
      "min_level": 11,
      "max_level": 14,
      "slots": 60,
      "held_item_groups": "",
      "morning_allowed": false,
      "day_allowed": false,
      "night_allowed": true
    },
    {
      "encounter": "kanto_route6_land",
      "pokemon": "vulpix",
      "min_level": 11,
      "max_level": 14,
      "slots": 4,
      "held_item_groups": "",
      "morning_allowed": true,
      "day_allowed": false,
      "night_allowed": false
    },
    {
      "encounter": "kanto_route6_land",
      "pokemon": "marill",
      "min_level": 12,
      "max_level": 14,
      "slots": 26,
      "held_item_groups": "",
      "morning_allowed": false,
      "day_allowed": true,
      "night_allowed": true
    },
    {
      "encounter": "kanto_route9_land1",
      "pokemon": "pidgey",
      "min_level": 15,
      "max_level": 19,
      "slots": 25,
      "held_item_groups": "",
      "morning_allowed": true,
      "day_allowed": true,
      "night_allowed": false
    },
    {
      "encounter": "kanto_route9_land1",
      "pokemon": "spearow",
      "min_level": 15,
      "max_level": 19,
      "slots": 85,
      "held_item_groups": "",
      "morning_allowed": true,
      "day_allowed": true,
      "night_allowed": true
    },
    {
      "encounter": "kanto_route9_land1",
      "pokemon": "rattata",
      "min_level": 15,
      "max_level": 19,
      "slots": 80,
      "held_item_groups": "",
      "morning_allowed": true,
      "day_allowed": true,
      "night_allowed": true
    },
    {
      "encounter": "kanto_route9_land1",
      "pokemon": "nidoran_f",
      "min_level": 15,
      "max_level": 19,
      "slots": 60,
      "held_item_groups": "",
      "morning_allowed": true,
      "day_allowed": true,
      "night_allowed": false
    },
    {
      "encounter": "kanto_route9_land1",
      "pokemon": "mankey",
      "min_level": 15,
      "max_level": 19,
      "slots": 50,
      "held_item_groups": "",
      "morning_allowed": false,
      "day_allowed": true,
      "night_allowed": false
    },
    {
      "encounter": "kanto_route9_land1",
      "pokemon": "growlithe",
      "min_level": 15,
      "max_level": 19,
      "slots": 30,
      "held_item_groups": "",
      "morning_allowed": false,
      "day_allowed": false,
      "night_allowed": true
    },
    {
      "encounter": "kanto_route9_land1",
      "pokemon": "tauros",
      "min_level": 15,
      "max_level": 19,
      "slots": 10,
      "held_item_groups": "",
      "morning_allowed": false,
      "day_allowed": true,
      "night_allowed": false
    },
    {
      "encounter": "kanto_route9_land1",
      "pokemon": "marill",
      "min_level": 15,
      "max_level": 19,
      "slots": 4,
      "held_item_groups": "",
      "morning_allowed": true,
      "day_allowed": false,
      "night_allowed": false
    },
    {
      "encounter": "kanto_route9_land1",
      "pokemon": "pichu",
      "min_level": 16,
      "max_level": 19,
      "slots": 1,
      "held_item_groups": "",
      "morning_allowed": false,
      "day_allowed": false,
      "night_allowed": true
    },
    {
      "encounter": "kanto_route9_land2",
      "pokemon": "pidgey",
      "min_level": 15,
      "max_level": 18,
      "slots": 25,
      "held_item_groups": "",
      "morning_allowed": true,
      "day_allowed": true,
      "night_allowed": false
    },
    {
      "encounter": "kanto_route9_land2",
      "pokemon": "rattata",
      "min_level": 15,
      "max_level": 18,
      "slots": 80,
      "held_item_groups": "",
      "morning_allowed": true,
      "day_allowed": true,
      "night_allowed": true
    },
    {
      "encounter": "kanto_route9_land2",
      "pokemon": "nidoran_f",
      "min_level": 15,
      "max_level": 18,
      "slots": 70,
      "held_item_groups": "",
      "morning_allowed": true,
      "day_allowed": true,
      "night_allowed": true
    },
    {
      "encounter": "kanto_route9_land2",
      "pokemon": "mankey",
      "min_level": 15,
      "max_level": 18,
      "slots": 55,
      "held_item_groups": "",
      "morning_allowed": true,
      "day_allowed": true,
      "night_allowed": false
    },
    {
      "encounter": "kanto_route9_land2",
      "pokemon": "spearow",
      "min_level": 15,
      "max_level": 18,
      "slots": 45,
      "held_item_groups": "",
      "morning_allowed": true,
      "day_allowed": true,
      "night_allowed": false
    },
    {
      "encounter": "kanto_route9_land2",
      "pokemon": "growlithe",
      "min_level": 15,
      "max_level": 18,
      "slots": 25,
      "held_item_groups": "",
      "morning_allowed": false,
      "day_allowed": false,
      "night_allowed": true
    },
    {
      "encounter": "kanto_route9_land2",
      "pokemon": "tauros",
      "min_level": 15,
      "max_level": 18,
      "slots": 10,
      "held_item_groups": "",
      "morning_allowed": false,
      "day_allowed": true,
      "night_allowed": false
    },
    {
      "encounter": "kanto_route9_land2",
      "pokemon": "marill",
      "min_level": 15,
      "max_level": 18,
      "slots": 4,
      "held_item_groups": "",
      "morning_allowed": true,
      "day_allowed": false,
      "night_allowed": false
    },
    {
      "encounter": "kanto_route9_land2",
      "pokemon": "pichu",
      "min_level": 16,
      "max_level": 18,
      "slots": 1,
      "held_item_groups": "",
      "morning_allowed": false,
      "day_allowed": false,
      "night_allowed": true
    },
    {
      "encounter": "kanto_route11_land",
      "pokemon": "pidgey",
      "min_level": 17,
      "max_level": 21,
      "slots": 25,
      "held_item_groups": "",
      "morning_allowed": true,
      "day_allowed": true,
      "night_allowed": false
    },
    {
      "encounter": "kanto_route11_land",
      "pokemon": "spearow",
      "min_level": 17,
      "max_level": 21,
      "slots": 80,
      "held_item_groups": "",
      "morning_allowed": true,
      "day_allowed": true,
      "night_allowed": true
    },
    {
      "encounter": "kanto_route11_land",
      "pokemon": "drowzee",
      "min_level": 17,
      "max_level": 21,
      "slots": 71,
      "held_item_groups": "",
      "morning_allowed": true,
      "day_allowed": true,
      "night_allowed": true
    },
    {
      "encounter": "kanto_route11_land",
      "pokemon": "rattata",
      "min_level": 17,
      "max_level": 21,
      "slots": 65,
      "held_item_groups": "",
      "morning_allowed": true,
      "day_allowed": true,
      "night_allowed": false
    },
    {
      "encounter": "kanto_route11_land",
      "pokemon": "magnemite",
      "min_level": 17,
      "max_level": 21,
      "slots": 50,
      "held_item_groups": "",
      "morning_allowed": true,
      "day_allowed": true,
      "night_allowed": false
    },
    {
      "encounter": "kanto_route11_land",
      "pokemon": "farfetch_d",
      "min_level": 17,
      "max_level": 21,
      "slots": 30,
      "held_item_groups": "",
      "morning_allowed": false,
      "day_allowed": false,
      "night_allowed": true
    },
    {
      "encounter": "kanto_route11_land",
      "pokemon": "mr_mime",
      "min_level": 17,
      "max_level": 21,
      "slots": 10,
      "held_item_groups": "",
      "morning_allowed": false,
      "day_allowed": true,
      "night_allowed": false
    },
    {
      "encounter": "kanto_route11_land",
      "pokemon": "elekid",
      "min_level": 17,
      "max_level": 21,
      "slots": 4,
      "held_item_groups": "",
      "morning_allowed": true,
      "day_allowed": false,
      "night_allowed": false
    },
    {
      "encounter": "kanto_mtmoon_cave",
      "pokemon": "zubat",
      "min_level": 8,
      "max_level": 13,
      "slots": 80,
      "held_item_groups": "",
      "morning_allowed": true,
      "day_allowed": true,
      "night_allowed": false
    },
    {
      "encounter": "kanto_mtmoon_cave",
      "pokemon": "geodude",
      "min_level": 8,
      "max_level": 13,
      "slots": 70,
      "held_item_groups": "",
      "morning_allowed": false,
      "day_allowed": true,
      "night_allowed": true
    },
    {
      "encounter": "kanto_mtmoon_cave",
      "pokemon": "paras",
      "min_level": 8,
      "max_level": 13,
      "slots": 55,
      "held_item_groups": "",
      "morning_allowed": true,
      "day_allowed": true,
      "night_allowed": false
    },
    {
      "encounter": "kanto_mtmoon_cave",
      "pokemon": "clefairy",
      "min_level": 8,
      "max_level": 13,
      "slots": 45,
      "held_item_groups": "",
      "morning_allowed": false,
      "day_allowed": true,
      "night_allowed": false
    },
    {
      "encounter": "kanto_mtmoon_cave",
      "pokemon": "sandshrew",
      "min_level": 8,
      "max_level": 13,
      "slots": 30,
      "held_item_groups": "",
      "morning_allowed": false,
      "day_allowed": false,
      "night_allowed": true
    },
    {
      "encounter": "kanto_mtmoon_cave",
      "pokemon": "cleffa",
      "min_level": 8,
      "max_level": 13,
      "slots": 3,
      "held_item_groups": "",
      "morning_allowed": true,
      "day_allowed": false,
      "night_allowed": false
    },
    {
      "encounter": "kanto_mtmoon_cave",
      "pokemon": "igglybuff",
      "min_level": 9,
      "max_level": 13,
      "slots": 2,
      "held_item_groups": "",
      "morning_allowed": false,
      "day_allowed": false,
      "night_allowed": true
    },
    {
      "encounter": "kanto_rocktunnel_cave1",
      "pokemon": "zubat",
      "min_level": 16,
      "max_level": 22,
      "slots": 80,
      "held_item_groups": "",
      "morning_allowed": true,
      "day_allowed": true,
      "night_allowed": false
    },
    {
      "encounter": "kanto_rocktunnel_cave1",
      "pokemon": "geodude",
      "min_level": 16,
      "max_level": 22,
      "slots": 75,
      "held_item_groups": "",
      "morning_allowed": true,
      "day_allowed": true,
      "night_allowed": true
    },
    {
      "encounter": "kanto_rocktunnel_cave1",
      "pokemon": "machop",
      "min_level": 16,
      "max_level": 22,
      "slots": 50,
      "held_item_groups": "",
      "morning_allowed": true,
      "day_allowed": false,
      "night_allowed": false
    },
    {
      "encounter": "kanto_rocktunnel_cave1",
      "pokemon": "onix",
      "min_level": 16,
      "max_level": 22,
      "slots": 40,
      "held_item_groups": "",
      "morning_allowed": false,
      "day_allowed": true,
      "night_allowed": false
    },
    {
      "encounter": "kanto_rocktunnel_cave1",
      "pokemon": "golbat",
      "min_level": 16,
      "max_level": 22,
      "slots": 15,
      "held_item_groups": "",
      "morning_allowed": true,
      "day_allowed": false,
      "night_allowed": false
    },
    {
      "encounter": "kanto_rocktunnel_cave2",
      "pokemon": "zubat",
      "min_level": 16,
      "max_level": 21,
      "slots": 75,
      "held_item_groups": "",
      "morning_allowed": true,
      "day_allowed": true,
      "night_allowed": false
    },
    {
      "encounter": "kanto_rocktunnel_cave2",
      "pokemon": "geodude",
      "min_level": 16,
      "max_level": 21,
      "slots": 70,
      "held_item_groups": "",
      "morning_allowed": false,
      "day_allowed": true,
      "night_allowed": true
    },
    {
      "encounter": "kanto_rocktunnel_cave2",
      "pokemon": "machop",
      "min_level": 16,
      "max_level": 21,
      "slots": 55,
      "held_item_groups": "",
      "morning_allowed": true,
      "day_allowed": false,
      "night_allowed": false
    },
    {
      "encounter": "kanto_rocktunnel_cave2",
      "pokemon": "golbat",
      "min_level": 16,
      "max_level": 21,
      "slots": 40,
      "held_item_groups": "",
      "morning_allowed": false,
      "day_allowed": true,
      "night_allowed": false
    },
    {
      "encounter": "kanto_rocktunnel_cave2",
      "pokemon": "onix",
      "min_level": 16,
      "max_level": 21,
      "slots": 30,
      "held_item_groups": "",
      "morning_allowed": false,
      "day_allowed": false,
      "night_allowed": true
    },
    {
      "encounter": "kanto_diglettscave_cave1",
      "pokemon": "diglett",
      "min_level": 15,
      "max_level": 18,
      "slots": 140,
      "held_item_groups": "",
      "morning_allowed": true,
      "day_allowed": true,
      "night_allowed": false
    },
    {
      "encounter": "kanto_diglettscave_cave1",
      "pokemon": "sandshrew",
      "min_level": 15,
      "max_level": 18,
      "slots": 80,
      "held_item_groups": "",
      "morning_allowed": false,
      "day_allowed": true,
      "night_allowed": true
    },
    {
      "encounter": "kanto_diglettscave_cave1",
      "pokemon": "onix",
      "min_level": 15,
      "max_level": 18,
      "slots": 5,
      "held_item_groups": "",
      "morning_allowed": true,
      "day_allowed": false,
      "night_allowed": true
    },
    {
      "encounter": "kanto_diglettscave_cave2",
      "pokemon": "diglett",
      "min_level": 15,
      "max_level": 18,
      "slots": 130,
      "held_item_groups": "",
      "morning_allowed": true,
      "day_allowed": true,
      "night_allowed": false
    },
    {
      "encounter": "kanto_diglettscave_cave2",
      "pokemon": "sandshrew",
      "min_level": 15,
      "max_level": 18,
      "slots": 95,
      "held_item_groups": "",
      "morning_allowed": false,
      "day_allowed": true,
      "night_allowed": true
    },
    {
      "encounter": "kanto_diglettscave_cave2",
      "pokemon": "onix",
      "min_level": 15,
      "max_level": 18,
      "slots": 11,
      "held_item_groups": "",
      "morning_allowed": false,
      "day_allowed": true,
      "night_allowed": true
    },
    {
      "encounter": "kanto_diglettscave_cave2",
      "pokemon": "dunsparce",
      "min_level": 15,
      "max_level": 18,
      "slots": 4,
      "held_item_groups": "",
      "morning_allowed": true,
      "day_allowed": false,
      "night_allowed": false
    },
    {
      "encounter": "kanto_route9_fish",
      "pokemon": "poliwag",
      "min_level": 10,
      "max_level": 20,
      "slots": 50,
      "held_item_groups": "",
      "morning_allowed": true,
      "day_allowed": false,
      "night_allowed": false
    },
    {
      "encounter": "kanto_route9_fish",
      "pokemon": "goldeen",
      "min_level": 10,
      "max_level": 20,
      "slots": 45,
      "held_item_groups": "",
      "morning_allowed": false,
      "day_allowed": true,
      "night_allowed": false
    },
    {
      "encounter": "kanto_route9_fish",
      "pokemon": "magikarp",
      "min_level": 10,
      "max_level": 20,
      "slots": 35,
      "held_item_groups": "",
      "morning_allowed": true,
      "day_allowed": true,
      "night_allowed": true
    },
    {
      "encounter": "kanto_route9_fish",
      "pokemon": "horsea",
      "min_level": 10,
      "max_level": 20,
      "slots": 30,
      "held_item_groups": "",
      "morning_allowed": false,
      "day_allowed": false,
      "night_allowed": true
    },
    {
      "encounter": "kanto_route9_fish",
      "pokemon": "krabby",
      "min_level": 10,
      "max_level": 20,
      "slots": 25,
      "held_item_groups": "",
      "morning_allowed": true,
      "day_allowed": true,
      "night_allowed": false
    },
    {
      "encounter": "kanto_route9_fish",
      "pokemon": "remoraid",
      "min_level": 10,
      "max_level": 20,
      "slots": 10,
      "held_item_groups": "",
      "morning_allowed": true,
      "day_allowed": false,
      "night_allowed": false
    },
    {
      "encounter": "kanto_route9_fish",
      "pokemon": "chinchou",
      "min_level": 10,
      "max_level": 20,
      "slots": 5,
      "held_item_groups": "",
      "morning_allowed": false,
      "day_allowed": false,
      "night_allowed": true
    },
    {
      "encounter": "kanto_route9_water",
      "pokemon": "goldeen",
      "min_level": 12,
      "max_level": 20,
      "slots": 60,
      "held_item_groups": "",
      "morning_allowed": false,
      "day_allowed": true,
      "night_allowed": false
    },
    {
      "encounter": "kanto_route9_water",
      "pokemon": "poliwag",
      "min_level": 12,
      "max_level": 18,
      "slots": 50,
      "held_item_groups": "",
      "morning_allowed": true,
      "day_allowed": false,
      "night_allowed": false
    },
    {
      "encounter": "kanto_route9_water",
      "pokemon": "psyduck",
      "min_level": 14,
      "max_level": 20,
      "slots": 45,
      "held_item_groups": "",
      "morning_allowed": true,
      "day_allowed": true,
      "night_allowed": false
    },
    {
      "encounter": "kanto_route9_water",
      "pokemon": "horsea",
      "min_level": 14,
      "max_level": 20,
      "slots": 20,
      "held_item_groups": "",
      "morning_allowed": false,
      "day_allowed": false,
      "night_allowed": true
    },
    {
      "encounter": "kanto_route1_land",
      "pokemon": "spearow",
      "min_level": 3,
      "max_level": 4,
      "slots": 15,
      "held_item_groups": "",
      "morning_allowed": true,
      "day_allowed": true,
      "night_allowed": false
    },
    {
      "encounter": "kanto_route2_land",
      "pokemon": "spearow",
      "min_level": 4,
      "max_level": 7,
      "slots": 15,
      "held_item_groups": "",
      "morning_allowed": true,
      "day_allowed": true,
      "night_allowed": false
    },
    {
      "encounter": "kanto_route3_land",
      "pokemon": "rattata",
      "min_level": 6,
      "max_level": 8,
      "slots": 15,
      "held_item_groups": "",
      "morning_allowed": true,
      "day_allowed": true,
      "night_allowed": false
    },
    {
      "encounter": "kanto_route24_land",
      "pokemon": "hoppip",
      "min_level": 8,
      "max_level": 12,
      "slots": 10,
      "held_item_groups": "",
      "morning_allowed": false,
      "day_allowed": true,
      "night_allowed": false
    },
    {
      "encounter": "kanto_mtmoon_cave",
      "pokemon": "teddiursa",
      "min_level": 8,
      "max_level": 13,
      "slots": 10,
      "held_item_groups": "",
      "morning_allowed": true,
      "day_allowed": false,
      "night_allowed": false
    },
    {
      "encounter": "kanto_mtmoon_cave",
      "pokemon": "houndour",
      "min_level": 8,
      "max_level": 13,
      "slots": 10,
      "held_item_groups": "",
      "morning_allowed": false,
      "day_allowed": false,
      "night_allowed": true
    },
    {
      "encounter": "kanto_rocktunnel_cave1",
      "pokemon": "cubone",
      "min_level": 17,
      "max_level": 22,
      "slots": 14,
      "held_item_groups": "",
      "morning_allowed": false,
      "day_allowed": false,
      "night_allowed": true
    },
    {
      "encounter": "kanto_rocktunnel_cave1",
      "pokemon": "koffing",
      "min_level": 17,
      "max_level": 22,
      "slots": 10,
      "held_item_groups": "",
      "morning_allowed": false,
      "day_allowed": true,
      "night_allowed": false
    },
    {
      "encounter": "kanto_rocktunnel_cave2",
      "pokemon": "cubone",
      "min_level": 17,
      "max_level": 21,
      "slots": 20,
      "held_item_groups": "",
      "morning_allowed": false,
      "day_allowed": false,
      "night_allowed": true
    },
    {
      "encounter": "kanto_rocktunnel_cave2",
      "pokemon": "koffing",
      "min_level": 17,
      "max_level": 21,
      "slots": 15,
      "held_item_groups": "",
      "morning_allowed": false,
      "day_allowed": true,
      "night_allowed": false
    },
    {
      "encounter": "kanto_route6_land",
      "pokemon": "growlithe",
      "min_level": 11,
      "max_level": 14,
      "slots": 20,
      "held_item_groups": "",
      "morning_allowed": false,
      "day_allowed": true,
      "night_allowed": false
    },
    {
      "encounter": "shared_rocksmash",
      "pokemon": "sandshrew",
      "min_level": 8,
      "max_level": 18,
      "slots": 10,
      "held_item_groups": "",
      "morning_allowed": false,
      "day_allowed": true,
      "night_allowed": true
    },
    {
      "encounter": "shared_rocksmash",
      "pokemon": "dunsparce",
      "min_level": 10,
      "max_level": 20,
      "slots": 5,
      "held_item_groups": "",
      "morning_allowed": false,
      "day_allowed": true,
      "night_allowed": true
    },
    {
      "encounter": "shared_rocksmash",
      "pokemon": "shuckle",
      "min_level": 15,
      "max_level": 25,
      "slots": 2,
      "held_item_groups": "",
      "morning_allowed": false,
      "day_allowed": true,
      "night_allowed": true
    },
    {
      "encounter": "kanto_route2_land",
      "pokemon": "pichu",
      "min_level": 4,
      "max_level": 6,
      "slots": 2,
      "held_item_groups": "",
      "morning_allowed": false,
      "day_allowed": true,
      "night_allowed": false
    },
    {
      "encounter": "kanto_viridianforest_land",
      "pokemon": "pichu",
      "min_level": 5,
      "max_level": 6,
      "slots": 2,
      "held_item_groups": "",
      "morning_allowed": false,
      "day_allowed": true,
      "night_allowed": false
    },
    {
      "encounter": "kanto_route2_land",
      "pokemon": "bulbasaur",
      "min_level": 4,
      "max_level": 7,
      "slots": 5,
      "held_item_groups": "",
      "morning_allowed": true,
      "day_allowed": true,
      "night_allowed": true
    },
    {
      "encounter": "kanto_route3_land",
      "pokemon": "charmander",
      "min_level": 7,
      "max_level": 9,
      "slots": 5,
      "held_item_groups": "",
      "morning_allowed": true,
      "day_allowed": true,
      "night_allowed": true
    },
    {
      "encounter": "kanto_route24_land",
      "pokemon": "squirtle",
      "min_level": 9,
      "max_level": 12,
      "slots": 5,
      "held_item_groups": "",
      "morning_allowed": false,
      "day_allowed": true,
      "night_allowed": true
    },
    {
      "encounter": "kanto_viridian_land",
      "pokemon": "hoppip",
      "min_level": 3,
      "max_level": 4,
      "slots": 50,
      "held_item_groups": "",
      "morning_allowed": true,
      "day_allowed": true,
      "night_allowed": true
    },
    {
      "encounter": "kanto_viridian_land",
      "pokemon": "mareep",
      "min_level": 2,
      "max_level": 3,
      "slots": 20,
      "held_item_groups": "",
      "morning_allowed": true,
      "day_allowed": true,
      "night_allowed": false
    },
    {
      "encounter": "kanto_viridian_land",
      "pokemon": "sunkern",
      "min_level": 3,
      "max_level": 4,
      "slots": 10,
      "held_item_groups": "",
      "morning_allowed": true,
      "day_allowed": true,
      "night_allowed": false
    },
    {
      "encounter": "kanto_viridian_land",
      "pokemon": "gastly",
      "min_level": 2,
      "max_level": 5,
      "slots": 10,
      "held_item_groups": "",
      "morning_allowed": false,
      "day_allowed": false,
      "night_allowed": true
    },
    {
      "encounter": "kanto_route1_tree",
      "pokemon": "pineco",
      "min_level": 2,
      "max_level": 4,
      "slots": 10,
      "held_item_groups": "",
      "morning_allowed": true,
      "day_allowed": true,
      "night_allowed": true
    },
    {
      "encounter": "kanto_route1_tree",
      "pokemon": "sunkern",
      "min_level": 2,
      "max_level": 4,
      "slots": 10,
      "held_item_groups": "",
      "morning_allowed": false,
      "day_allowed": true,
      "night_allowed": false
    },
    {
      "encounter": "kanto_pewterglade_ground",
      "pokemon": "paras",
      "min_level": 6,
      "max_level": 7,
      "slots": 10,
      "held_item_groups": "",
      "morning_allowed": true,
      "day_allowed": true,
      "night_allowed": true
    },
    {
      "encounter": "kanto_pewterglade_ground",
      "pokemon": "dunsparce",
      "min_level": 6,
      "max_level": 7,
      "slots": 10,
      "held_item_groups": "",
      "morning_allowed": true,
      "day_allowed": true,
      "night_allowed": true
    },
    {
      "encounter": "kanto_pewterglade_ground",
      "pokemon": "diglett",
      "min_level": 6,
      "max_level": 7,
      "slots": 10,
      "held_item_groups": "",
      "morning_allowed": true,
      "day_allowed": true,
      "night_allowed": true
    },
    {
      "encounter": "kanto_pewterglade_tree",
      "pokemon": "spearow",
      "min_level": 6,
      "max_level": 7,
      "slots": 10,
      "held_item_groups": "",
      "morning_allowed": true,
      "day_allowed": true,
      "night_allowed": false
    },
    {
      "encounter": "kanto_pewterglade_tree",
      "pokemon": "pidgeotto",
      "min_level": 6,
      "max_level": 7,
      "slots": 10,
      "held_item_groups": "",
      "morning_allowed": true,
      "day_allowed": true,
      "night_allowed": false
    },
    {
      "encounter": "kanto_pewterglade_tree",
      "pokemon": "hoothoot",
      "min_level": 6,
      "max_level": 7,
      "slots": 10,
      "held_item_groups": "",
      "morning_allowed": false,
      "day_allowed": false,
      "night_allowed": true
    },
    {
      "encounter": "kanto_route1_tree",
      "pokemon": "hoothoot",
      "min_level": 1,
      "max_level": 4,
      "slots": 10,
      "held_item_groups": "",
      "morning_allowed": false,
      "day_allowed": false,
      "night_allowed": true
    },
    {
      "encounter": "kanto_mtmoon_ore",
      "pokemon": "diglett",
      "min_level": 8,
      "max_level": 13,
      "slots": 10,
      "held_item_groups": "",
      "morning_allowed": true,
      "day_allowed": true,
      "night_allowed": true
    },
    {
      "encounter": "kanto_mtmoon_ore",
      "pokemon": "sandshrew",
      "min_level": 8,
      "max_level": 13,
      "slots": 10,
      "held_item_groups": "",
      "morning_allowed": true,
      "day_allowed": true,
      "night_allowed": true
    },
    {
      "encounter": "kanto_mtmoon_ore",
      "pokemon": "phanpy",
      "min_level": 8,
      "max_level": 13,
      "slots": 5,
      "held_item_groups": "",
      "morning_allowed": true,
      "day_allowed": true,
      "night_allowed": true
    },
    {
      "encounter": "kanto_mtmoon_ground",
      "pokemon": "paras",
      "min_level": 9,
      "max_level": 15,
      "slots": 10,
      "held_item_groups": "",
      "morning_allowed": true,
      "day_allowed": true,
      "night_allowed": true
    },
    {
      "encounter": "kanto_mtmoon_ground",
      "pokemon": "tyrogue",
      "min_level": 1,
      "max_level": 1,
      "slots": 1,
      "held_item_groups": "",
      "morning_allowed": true,
      "day_allowed": true,
      "night_allowed": true
    },
    {
      "encounter": "kanto_mtmoon_ore",
      "pokemon": "misdreavus",
      "min_level": 1,
      "max_level": 1,
      "slots": 1,
      "held_item_groups": "",
      "morning_allowed": false,
      "day_allowed": false,
      "night_allowed": true
    },
    {
      "encounter": "kanto_diglettscave_cave2",
      "pokemon": "dugtrio",
      "min_level": 18,
      "max_level": 21,
      "slots": 25,
      "held_item_groups": "",
      "morning_allowed": true,
      "day_allowed": true,
      "night_allowed": false
    },
    {
      "encounter": "kanto_diglettscave_cave2",
      "pokemon": "sneasel",
      "min_level": 15,
      "max_level": 18,
      "slots": 3,
      "held_item_groups": "",
      "morning_allowed": false,
      "day_allowed": false,
      "night_allowed": true
    },
    {
      "encounter": "kanto_viridian_land",
      "pokemon": "aipom",
      "min_level": 2,
      "max_level": 5,
      "slots": 10,
      "held_item_groups": "",
      "morning_allowed": true,
      "day_allowed": false,
      "night_allowed": false
    },
    {
      "encounter": "kanto_viridian_land",
      "pokemon": "slowpoke",
      "min_level": 3,
      "max_level": 4,
      "slots": 10,
      "held_item_groups": "",
      "morning_allowed": false,
      "day_allowed": true,
      "night_allowed": false
    },
    {
      "encounter": "kanto_route24_ore",
      "pokemon": "phanpy",
      "min_level": 8,
      "max_level": 12,
      "slots": 10,
      "held_item_groups": "",
      "morning_allowed": true,
      "day_allowed": true,
      "night_allowed": true
    },
    {
      "encounter": "kanto_route24_ore",
      "pokemon": "magnemite",
      "min_level": 8,
      "max_level": 12,
      "slots": 10,
      "held_item_groups": "",
      "morning_allowed": true,
      "day_allowed": true,
      "night_allowed": true
    },
    {
      "encounter": "kanto_route11_resource",
      "pokemon": "paras",
      "min_level": 15,
      "max_level": 20,
      "slots": 10,
      "held_item_groups": "",
      "morning_allowed": true,
      "day_allowed": false,
      "night_allowed": false
    },
    {
      "encounter": "kanto_route11_resource",
      "pokemon": "misdreavus",
      "min_level": 15,
      "max_level": 20,
      "slots": 10,
      "held_item_groups": "",
      "morning_allowed": false,
      "day_allowed": false,
      "night_allowed": true
    },
    {
      "encounter": "kanto_route2_land",
      "pokemon": "ponyta",
      "min_level": 4,
      "max_level": 6,
      "slots": 8,
      "held_item_groups": "",
      "morning_allowed": true,
      "day_allowed": true,
      "night_allowed": false
    },
    {
      "encounter": "kanto_mtmoon_cave",
      "pokemon": "onix",
      "min_level": 9,
      "max_level": 12,
      "slots": 25,
      "held_item_groups": "",
      "morning_allowed": true,
      "day_allowed": true,
      "night_allowed": true
    },
    {
      "encounter": "kanto_route11_land",
      "pokemon": "wooper",
      "min_level": 17,
      "max_level": 21,
      "slots": 25,
      "held_item_groups": "",
      "morning_allowed": true,
      "day_allowed": true,
      "night_allowed": true
    },
    {
      "encounter": "kanto_route11_resource",
      "pokemon": "ariados",
      "min_level": 15,
      "max_level": 20,
      "slots": 10,
      "held_item_groups": "",
      "morning_allowed": true,
      "day_allowed": true,
      "night_allowed": false
    },
    {
      "encounter": "kanto_route11_resource",
      "pokemon": "ledian",
      "min_level": 15,
      "max_level": 20,
      "slots": 10,
      "held_item_groups": "",
      "morning_allowed": false,
      "day_allowed": true,
      "night_allowed": true
    },
    {
      "encounter": "kanto_route6_land",
      "pokemon": "skiploom",
      "min_level": 13,
      "max_level": 15,
      "slots": 25,
      "held_item_groups": "",
      "morning_allowed": true,
      "day_allowed": true,
      "night_allowed": true
    },
    {
      "encounter": "kanto_route6_land",
      "pokemon": "furret",
      "min_level": 13,
      "max_level": 15,
      "slots": 25,
      "held_item_groups": "",
      "morning_allowed": true,
      "day_allowed": true,
      "night_allowed": true
    },
    {
      "encounter": "kanto_evergreengrove_land",
      "pokemon": "shuckle",
      "min_level": 11,
      "max_level": 14,
      "slots": 10,
      "held_item_groups": "",
      "morning_allowed": true,
      "day_allowed": true,
      "night_allowed": true
    },
    {
      "encounter": "kanto_evergreengrove_land",
      "pokemon": "mareep",
      "min_level": 11,
      "max_level": 14,
      "slots": 10,
      "held_item_groups": "",
      "morning_allowed": true,
      "day_allowed": true,
      "night_allowed": true
    },
    {
      "encounter": "kanto_evergreengrove_land",
      "pokemon": "magby",
      "min_level": 11,
      "max_level": 11,
      "slots": 1,
      "held_item_groups": "",
      "morning_allowed": false,
      "day_allowed": true,
      "night_allowed": false
    },
    {
      "encounter": "kanto_evergreengrove_land",
      "pokemon": "elekid",
      "min_level": 11,
      "max_level": 11,
      "slots": 1,
      "held_item_groups": "",
      "morning_allowed": true,
      "day_allowed": false,
      "night_allowed": false
    },
    {
      "encounter": "kanto_evergreengrove_land",
      "pokemon": "eevee",
      "min_level": 11,
      "max_level": 11,
      "slots": 5,
      "held_item_groups": "",
      "morning_allowed": true,
      "day_allowed": false,
      "night_allowed": false
    },
    {
      "encounter": "kanto_evergreengrove_land",
      "pokemon": "voltorb",
      "min_level": 11,
      "max_level": 14,
      "slots": 10,
      "held_item_groups": "",
      "morning_allowed": true,
      "day_allowed": true,
      "night_allowed": true
    },
    {
      "encounter": "kanto_evergreengrove_land",
      "pokemon": "sneasel",
      "min_level": 11,
      "max_level": 14,
      "slots": 1,
      "held_item_groups": "",
      "morning_allowed": false,
      "day_allowed": false,
      "night_allowed": true
    },
    {
      "encounter": "kanto_route24_land",
      "pokemon": "abra",
      "min_level": 8,
      "max_level": 12,
      "slots": 4,
      "held_item_groups": "",
      "morning_allowed": true,
      "day_allowed": true,
      "night_allowed": true
    },
    {
      "encounter": "kanto_route24_land",
      "pokemon": "sunkern",
      "min_level": 8,
      "max_level": 12,
      "slots": 10,
      "held_item_groups": "",
      "morning_allowed": false,
      "day_allowed": true,
      "night_allowed": false
    },
    {
      "encounter": "kanto_encounter_26",
      "pokemon": "aggron",
      "min_level": 5,
      "max_level": 10,
      "slots": 10,
      "held_item_groups": "",
      "morning_allowed": true,
      "day_allowed": true,
      "night_allowed": true
    }
  ],
  "total_slots_combined": 38673
}
