{
  "unique_name": "kanto_viridianforest_lass_mia",
  "display_name": "Lass Mia",
  "sprite": null,
  "rank": "Novice",
  "music_key": null,
  "payout_base": 200,
  "payout_per_level": 10,
  "badge_award": null,
  "items": [],
  "initial_field": null,
  "team": [
    {
      "species": "caterpie",
      "ability": "shield_dust",
      "nature": "timid",
      "gender": "female",
      "level_offset": -1,
      "iv_hp": 14,
      "iv_atk": 10,
      "iv_def": 12,
      "iv_spa": 13,
      "iv_spd": 12,
      "iv_spe": 16,
      "moves": []
    },
    {
      "species": "weedle",
      "ability": "shield_dust",
      "nature": "jolly",
      "gender": "female",
      "level_offset": -1,
      "iv_hp": 13,
      "iv_atk": 13,
      "iv_def": 12,
      "iv_spa": 8,
      "iv_spd": 11,
      "iv_spe": 15,
      "moves": []
    },
    {
      "species": "hoothoot",
      "ability": "insomnia",
      "nature": "modest",
      "gender": "female",
      "level_offset": -1,
      "iv_hp": 16,
      "iv_atk": 9,
      "iv_def": 12,
      "iv_spa": 14,
      "iv_spd": 14,
      "iv_spe": 12,
      "moves": []
    }
  ],
  "dialogue": {
    "start": "I love the forest! All my Pokemon were caught right here among the trees!",
    "loss": "You're a natural, just like my forest Pokemon!",
    "post_defeat": "Hoothoot come out at dusk. Their calls echo through the whole forest."
  },
  "rebattle": "daily",
  "scaling_min_level": 6
}
