{
  "unique_name": "kanto_vermilion_gym_sailor_sally",
  "display_name": "Sailor Sally",
  "sprite": null,
  "rank": "Amateur",
  "music_key": null,
  "payout_base": 560,
  "payout_per_level": 24,
  "badge_award": null,
  "items": [],
  "initial_field": null,
  "team": [
    {
      "species": "magnemite",
      "ability": "magnet_pull",
      "nature": "modest",
      "gender": "genderless",
      "level_offset": 1,
      "iv_hp": 18,
      "iv_atk": 11,
      "iv_def": 18,
      "iv_spa": 20,
      "iv_spd": 16,
      "iv_spe": 14,
      "moves": [
        "shock_wave",
        "supersonic",
        "sonic_boom",
        "thunder_wave"
      ]
    },
    {
      "species": "voltorb",
      "ability": "static",
      "nature": "timid",
      "gender": "genderless",
      "level_offset": 1,
      "iv_hp": 17,
      "iv_atk": 12,
      "iv_def": 16,
      "iv_spa": 17,
      "iv_spd": 16,
      "iv_spe": 20,
      "moves": [
        "tackle",
        "screech",
        "sonic_boom",
        "spark"
      ]
    },
    {
      "species": "pidgey",
      "ability": "keen_eye",
      "nature": "timid",
      "gender": "male",
      "level_offset": 1,
      "iv_hp": 18,
      "iv_atk": 18,
      "iv_def": 16,
      "iv_spa": 12,
      "iv_spd": 14,
      "iv_spe": 14,
      "moves": [
        "tackle",
        "sand_attack",
        "gust",
        "quick_attack"
      ]
    }
  ],
  "dialogue": {
    "start": "Aye aye! I may be a sailor but I switched to electric types when I joined Surge's crew!",
    "loss": "You've got the spark of a champion, kid!",
    "post_defeat": "Lt. Surge was a real soldier. He knows battle strategy like no one else."
  },
  "rebattle": "daily"
}
